LICENCE.txt
MANIFEST.in
README.rst
setup.py
examples/basics.py
examples/canvas_editor.py
examples/cinematic_evolution.py
examples/custom_optimization.py
vmfactory/Vmaze.py
vmfactory/Vmaze_HT.py
vmfactory/Vmaze_NHT.py
vmfactory/__init__.py
vmfactory/version.py
vmfactory.egg-info/PKG-INFO
vmfactory.egg-info/SOURCES.txt
vmfactory.egg-info/dependency_links.txt
vmfactory.egg-info/requires.txt
vmfactory.egg-info/top_level.txt
vmfactory/canvas/__init__.py
vmfactory/canvas/canvas_editor.py
vmfactory/canvas/diamond.py
vmfactory/canvas/squares_grid.py
vmfactory/canvas/stacked_cubes.py
vmfactory/canvas/star.py
vmfactory/game/Game.py
vmfactory/game/__init__.py
vmfactory/game/maze_levels.py