Metadata-Version: 1.0
Name: vmfactory
Version: 0.1.03
Summary: Automatic generation of Viennese mazes with Python
Home-page: UNKNOWN
Author: Zulko
Author-email: UNKNOWN
License: see LICENSE.txt
Keywords: Viennese mazes
Platform: UNKNOWN
